bestree/__init__.py
bestree/bestree.py
bestree-0.1.0.dist-info/LICENSE
bestree-0.1.0.dist-info/METADATA
bestree-0.1.0.dist-info/WHEEL
bestree-0.1.0.dist-info/top_level.txt
bestree-0.1.0.dist-info/RECORD
