Metadata-Version: 2.1
Name: bestree
Version: 0.1.0
Summary: A Python package for finding the best decision tree parameters.
Home-page: UNKNOWN
Author: CodingLive
Author-email: <rootcode@duck.com>
License: UNKNOWN
Keywords: decision tree,decision tree parameters,best tree parameters
Platform: UNKNOWN
License-File: LICENSE
Requires-Dist: numpy
Requires-Dist: scikit-learn
Requires-Dist: pandas
